ratio_analysis/__init__.py
ratio_analysis/ratioanalysistool.py
financial_ratio_analysis-0.0.1.dist-info/LICENSE
financial_ratio_analysis-0.0.1.dist-info/METADATA
financial_ratio_analysis-0.0.1.dist-info/WHEEL
financial_ratio_analysis-0.0.1.dist-info/top_level.txt
financial_ratio_analysis-0.0.1.dist-info/RECORD
